project_raccoon/__init__.py
project_raccoon/__main__.py
project_raccoon/src/__init__.py
project_raccoon/src/typing.py
project_raccoon/src/util.py
project_raccoon/src/data/__init__.py
project_raccoon/src/data/monomers.json
project_raccoon/src/data/monomers.py
project_raccoon/src/data/structs.py
project_raccoon/src/functions/__init__.py
project_raccoon/src/functions/standard.py
project_raccoon/src/functions/util.py
project_raccoon/src/ui/__init__.py
project_raccoon/src/ui/head.py
project_raccoon/src/ui/user_interface.py
project_raccoon/tests/__init__.py
project_raccoon/tests/__main__.py
project_raccoon/tests/unit/__init__.py
project_raccoon/tests/unit/test_data.py
project_raccoon/tests/unit/test_functions.py
project_raccoon/tests/unit/test_monomers_json.py
project_raccoon/tests/unit/test_pdb_file.py
project_raccoon/tests/unit/test_ui.py
project_raccoon/tests/unit/data/alanine.bs
project_raccoon/tests/unit/data/out.pdb
project_raccoon/tests/unit/data/out.xyz
project_raccoon/tests/unit/data/seq_FHFHFXG_PEO_GXFHFHF.txt
project_raccoon/tests/unit/data/seq_failure.txt
project_raccoon-1.1.0.dist-info/LICENSE
project_raccoon-1.1.0.dist-info/METADATA
project_raccoon-1.1.0.dist-info/WHEEL
project_raccoon-1.1.0.dist-info/entry_points.txt
project_raccoon-1.1.0.dist-info/top_level.txt
project_raccoon-1.1.0.dist-info/RECORD
