Metadata-Version: 2.1
Name: project_raccoon
Version: 1.1.0
Summary: ProjectRaccoon is a Python tool designed for the generation of PDB (Protein Data Bank) files for polymer peptide conjugates, polypeptides, and polymers in a building block fashion.
Home-page: https://github.com/moritzobenauer/ProjectRaccoon
Author: Moritz L. Obenauer, Kai N. Spauszus.
Classifier: Programming Language :: Python :: 3
Classifier: License :: OSI Approved :: GNU General Public License (GPL)
Classifier: Operating System :: OS Independent
Classifier: Natural Language :: English
Requires-Python: >=3.11
License-File: LICENSE
Requires-Dist: biopandas ==0.4.1
Requires-Dist: numpy ==1.26.3
Requires-Dist: pandas ==2.1.4
Requires-Dist: py3Dmol ==2.0.4
Requires-Dist: questionary ==2.0.1
Requires-Dist: rich ==13.7.0
Requires-Dist: scipy ==1.11.4
Requires-Dist: setuptools ==68.2.2
Requires-Dist: tqdm ==4.66.1
